lightstreamer_client/__init__.py
lightstreamer_client-0.1.dist-info/LICENSE
lightstreamer_client-0.1.dist-info/METADATA
lightstreamer_client-0.1.dist-info/WHEEL
lightstreamer_client-0.1.dist-info/top_level.txt
lightstreamer_client-0.1.dist-info/RECORD
