Metadata-Version: 2.1
Name: lightstreamer-client
Version: 0.1
Summary: Lightstreamer Python client
Home-page: https://github.com/wjszlachta/lightstreamer-client
Author: Wojciech Szlachta
Author-email: wojciech@szlachta.net
License: UNKNOWN
Project-URL: Bug Reports, https://github.com/wjszlachta/lightstreamer-client/issues
Project-URL: Source, https://github.com/wjszlachta/lightstreamer-client
Keywords: lightstreamer
Platform: UNKNOWN
Classifier: Development Status :: 3 - Alpha
Classifier: Intended Audience :: Developers
Classifier: Topic :: Software Development :: Libraries :: Python Modules
Classifier: License :: OSI Approved :: Apache Software License
Classifier: Programming Language :: Python :: 3
